Metadata-Version: 2.1
Name: wcdeetlist
Version: 0.0.0.4.2
Summary: Web Crawler for https://deetlist.com
Author: Marcuth
Author-email: marcuth2006@gmail.com
License: MIT License
Keywords: scrapper scraper crawler deetlist
License-File: LICENSE
